smeagol/__init__.py
smeagol/golum_to_hanabi.py
smeagol/lensing_models.py
smeagol/marginalized_likelihood.py
smeagol/reweight_with_population_model.py
smeagol_gw-0.0.1.dist-info/LICENSE
smeagol_gw-0.0.1.dist-info/METADATA
smeagol_gw-0.0.1.dist-info/WHEEL
smeagol_gw-0.0.1.dist-info/top_level.txt
smeagol_gw-0.0.1.dist-info/RECORD
